odoo/addons/hr_personal_equipment_request/README.rst
odoo/addons/hr_personal_equipment_request/__init__.py
odoo/addons/hr_personal_equipment_request/__manifest__.py
odoo/addons/hr_personal_equipment_request/i18n/de.po
odoo/addons/hr_personal_equipment_request/i18n/es.po
odoo/addons/hr_personal_equipment_request/i18n/es_PA.po
odoo/addons/hr_personal_equipment_request/i18n/hr_personal_equipment_request.pot
odoo/addons/hr_personal_equipment_request/i18n/it.po
odoo/addons/hr_personal_equipment_request/i18n/pt_BR.po
odoo/addons/hr_personal_equipment_request/models/__init__.py
odoo/addons/hr_personal_equipment_request/models/hr_employee.py
odoo/addons/hr_personal_equipment_request/models/hr_personal_equipment.py
odoo/addons/hr_personal_equipment_request/models/hr_personal_equipment_request.py
odoo/addons/hr_personal_equipment_request/models/product_template.py
odoo/addons/hr_personal_equipment_request/readme/CONTRIBUTORS.rst
odoo/addons/hr_personal_equipment_request/readme/DESCRIPTION.rst
odoo/addons/hr_personal_equipment_request/readme/USAGE.rst
odoo/addons/hr_personal_equipment_request/security/hr_personal_equipment_request_security.xml
odoo/addons/hr_personal_equipment_request/security/ir.model.access.csv
odoo/addons/hr_personal_equipment_request/static/description/icon.png
odoo/addons/hr_personal_equipment_request/static/description/index.html
odoo/addons/hr_personal_equipment_request/tests/__init__.py
odoo/addons/hr_personal_equipment_request/tests/test_hr_personal_equipment_request.py
odoo/addons/hr_personal_equipment_request/views/hr_employee.xml
odoo/addons/hr_personal_equipment_request/views/hr_personal_equipment.xml
odoo/addons/hr_personal_equipment_request/views/hr_personal_equipment_request.xml
odoo/addons/hr_personal_equipment_request/views/product_template.xml
odoo14_addon_hr_personal_equipment_request-14.0.1.0.1.dist-info/METADATA
odoo14_addon_hr_personal_equipment_request-14.0.1.0.1.dist-info/WHEEL
odoo14_addon_hr_personal_equipment_request-14.0.1.0.1.dist-info/top_level.txt
odoo14_addon_hr_personal_equipment_request-14.0.1.0.1.dist-info/RECORD
